{".class": "MypyFile", "_fullname": "item", "_name": null, "is_stub": false, "names": {".class": "SymbolTable", "Enum": {".class": "SymbolTableNode", "cross_ref": "enum.Enum", "kind": "Gdef"}, "ItmType": {".class": "SymbolTableNode", "kind": "Gdef", "node": {".class": "TypeInfo", "_promote": null, "abstract_attributes": [], "bases": ["enum.Enum"], "declared_metaclass": null, "defn": {".class": "ClassDef", "fullname": "item.ItmType", "name": "ItmType", "type_vars": []}, "flags": ["is_enum"], "fullname": "item.ItmType", "metaclass_type": "enum.EnumMeta", "module_name": "item", "names": {".class": "SymbolTable", "ARM1": {".class": "SymbolTableNode", "kind": "Mdef", "node": {".class": "Var", "flags": ["is_ready", "is_initialized_in_class"], "fullname": "item.ItmType.ARM1", "name": "ARM1", "type": "builtins.int"}}, "ARM2": {".class": "SymbolTableNode", "kind": "Mdef", "node": {".class": "Var", "flags": ["is_ready", "is_initialized_in_class"], "fullname": "item.ItmType.ARM2", "name": "ARM2", "type": "builtins.int"}}, "BODY": {".class": "SymbolTableNode", "kind": "Mdef", "node": {".class": "Var", "flags": ["is_ready", "is_initialized_in_class"], "fullname": "item.ItmType.BODY", "name": "BODY", "type": "builtins.int"}}, "HEAD": {".class": "SymbolTableNode", "kind": "Mdef", "node": {".class": "Var", "flags": ["is_ready", "is_initialized_in_class"], "fullname": "item.ItmType.HEAD", "name": "HEAD", "type": "builtins.int"}}, "LEGS": {".class": "SymbolTableNode", "kind": "Mdef", "node": {".class": "Var", "flags": ["is_ready", "is_initialized_in_class"], "fullname": "item.ItmType.LEGS", "name": "LEGS", "type": "builtins.int"}}, "TRK1": {".class": "SymbolTableNode", "kind": "Mdef", "node": {".class": "Var", "flags": ["is_ready", "is_initialized_in_class"], "fullname": "item.ItmType.TRK1", "name": "TRK1", "type": "builtins.int"}}, "TRK2": {".class": "SymbolTableNode", "kind": "Mdef", "node": {".class": "Var", "flags": ["is_ready", "is_initialized_in_class"], "fullname": "item.ItmType.TRK2", "name": "TRK2", "type": "builtins.int"}}}, "protocol_members": null, "tuple_type": null, "type_vars": [], "typeddict_type": null}}, "__doc__": {".class": "SymbolTableNode", "kind": "Gdef", "node": {".class": "Var", "flags": ["is_ready"], "fullname": "item.__doc__", "name": "__doc__", "type": "builtins.str"}}, "__file__": {".class": "SymbolTableNode", "kind": "Gdef", "node": {".class": "Var", "flags": ["is_ready"], "fullname": "item.__file__", "name": "__file__", "type": "builtins.str"}}, "__name__": {".class": "SymbolTableNode", "kind": "Gdef", "node": {".class": "Var", "flags": ["is_ready"], "fullname": "item.__name__", "name": "__name__", "type": "builtins.str"}}, "__package__": {".class": "SymbolTableNode", "kind": "Gdef", "node": {".class": "Var", "flags": ["is_ready"], "fullname": "item.__package__", "name": "__package__", "type": "builtins.str"}}}, "path": "/home/acc/repos/gambeson/item.py"}
